multipie2/__init__.py
multipie2/binary_data/atomic_multipole.pkl
multipie2/binary_data/atomic_multipole_group.pkl
multipie2/binary_data/group.pkl
multipie2/binary_data/harmonics.pkl
multipie2/binary_data/harmonics_multipole.pkl
multipie2/binary_data/harmonics_spherical.pkl
multipie2/binary_data/info.pkl
multipie2/binary_data/rep_matrix.pkl
multipie2/binary_data/root_cluster.pkl
multipie2/binary_data/so_matrix.pkl
multipie2/data/data_character_table.py
multipie2/data/data_compatibility_relation.py
multipie2/data/data_crystal.py
multipie2/data/data_definition.py
multipie2/data/data_group.py
multipie2/data/data_symmetry_operation.py
multipie2/data/data_top_harmonics.py
multipie2/data/data_wyckoff_bond.py
multipie2/data/data_wyckoff_site.py
multipie2/util/util.py
multipie2/util/util_binary.py
multipie2/util/util_cluster.py
multipie2/util/util_crystal.py
multipie2/util/util_plot.py
multipie2/util/util_spherical_harmonics.py
multipie2/util/util_symmetry_operation.py
multipie2/util/util_symmetry_operation_spherical.py
multipie2/util/util_tag.py
multipie2/util/util_wyckoff.py
multipie2/util/more/test_util_more.py
multipie2/util/more/util_more.py
multipie2/util/more/util_vector.py
multipie2/util/more/util_wyckoff.py
multipie2-2.0.0.dist-info/LICENSE
multipie2-2.0.0.dist-info/METADATA
multipie2-2.0.0.dist-info/WHEEL
multipie2-2.0.0.dist-info/entry_points.txt
multipie2-2.0.0.dist-info/top_level.txt
multipie2-2.0.0.dist-info/RECORD
